music_assistant_frontend/__init__.py
music_assistant_frontend/apple-touch-icon.png
music_assistant_frontend/favicon.ico
music_assistant_frontend/favicon.svg
music_assistant_frontend/index.html
music_assistant_frontend/manifest.webmanifest
music_assistant_frontend/pwa-192x192.png
music_assistant_frontend/pwa-512x512.png
music_assistant_frontend/py.typed
music_assistant_frontend/robots.txt
music_assistant_frontend/sw.js
music_assistant_frontend/workbox-27b29e6f.js
music_assistant_frontend/assets/AddProvider-13efb0c6.js
music_assistant_frontend/assets/AlbumDetails-02d8e439.js
music_assistant_frontend/assets/ArtistDetails-bc4d210c.js
music_assistant_frontend/assets/BrowseView-99ca7843.js
music_assistant_frontend/assets/Default-61898bf6.css
music_assistant_frontend/assets/Default-630de139.js
music_assistant_frontend/assets/EditConfig-db03c2e9.css
music_assistant_frontend/assets/EditConfig.vue_vue_type_style_index_0_lang-1aa941c6.js
music_assistant_frontend/assets/EditPlayer-ce8d13fa.js
music_assistant_frontend/assets/EditProvider-e5dc9008.js
music_assistant_frontend/assets/HomeView-8c35b088.js
music_assistant_frontend/assets/HomeView-f559b858.css
music_assistant_frontend/assets/InfoHeader-23670b62.css
music_assistant_frontend/assets/InfoHeader.vue_vue_type_style_index_0_lang-875a141a.js
music_assistant_frontend/assets/ItemsListing-519a2b61.css
music_assistant_frontend/assets/ItemsListing.vue_vue_type_script_setup_true_lang-db49cd4a.js
music_assistant_frontend/assets/KFOkCnqEu92Fr1MmgVxEIzIFKw-8007dfe8.woff2
music_assistant_frontend/assets/KFOkCnqEu92Fr1MmgVxFIzIFKw-8e48cf20.woff2
music_assistant_frontend/assets/KFOkCnqEu92Fr1MmgVxGIzIFKw-10b31f4c.woff2
music_assistant_frontend/assets/KFOkCnqEu92Fr1MmgVxHIzIFKw-ca7eea0c.woff2
music_assistant_frontend/assets/KFOkCnqEu92Fr1MmgVxIIzI-0f303f31.woff2
music_assistant_frontend/assets/KFOkCnqEu92Fr1MmgVxLIzIFKw-8c3798e3.woff2
music_assistant_frontend/assets/KFOkCnqEu92Fr1MmgVxMIzIFKw-638764dc.woff2
music_assistant_frontend-20230616.0.dist-info/LICENSE
music_assistant_frontend-20230616.0.dist-info/METADATA
music_assistant_frontend-20230616.0.dist-info/WHEEL
music_assistant_frontend-20230616.0.dist-info/top_level.txt
music_assistant_frontend-20230616.0.dist-info/RECORD
