Metadata-Version: 2.1
Name: music-assistant-frontend
Version: 20230616.0
Summary: The Music Assistant frontend
Author-email: The Music Assistant Authors <m.vanderveldt@outlook.com>
License: Apache-2.0
Project-URL: Homepage, https://github.com/music-assistant/frontend
Platform: any
Requires-Python: >=3.9.0
License-File: LICENSE
